manas_ai/__init__.py
manas_ai/agent.py
manas_ai/base.py
manas_ai/chat.py
manas_ai/flow.py
manas_ai/llm.py
manas_ai/models.py
manas_ai/nodes/__init__.py
manas_ai/nodes/api_node.py
manas_ai/nodes/browser_node.py
manas_ai/nodes/document_node.py
manas_ai/nodes/factory.py
manas_ai/nodes/protocol.py
manas_ai/nodes/qa_node.py
manas_ai/nodes/tool_node.py
manas_ai/providers/__init__.py
manas_ai/providers/anthropic.py
manas_ai/providers/base.py
manas_ai/providers/factory.py
manas_ai/providers/huggingface.py
manas_ai/providers/middleware.py
manas_ai/providers/mock.py
manas_ai/providers/ollama.py
manas_ai/providers/openai.py
manas_ai/providers/protocol.py
manas_ai/rag.py
manas_ai/tokenizers.py
manas_ai/vectorstores/__init__.py
manas_ai/vectorstores/base.py
manas_ai/vectorstores/chroma.py
manas_ai/vectorstores/factory.py
manas_ai/vectorstores/faiss.py
manas_ai/vectorstores/pinecone.py
manas_ai/vectorstores/protocol.py
manas_ai-0.2.1.dist-info/LICENSE
manas_ai-0.2.1.dist-info/METADATA
manas_ai-0.2.1.dist-info/WHEEL
manas_ai-0.2.1.dist-info/RECORD
