Metadata-Version: 2.1
Name: manas-ai
Version: 0.2.1
Summary: A framework for building LLM-powered applications with intelligent agents, task decomposition, and RAG
Home-page: https://github.com/arkokoley/manas
License: MIT
Keywords: llm,agents,rag,ai,nlp
Author: Gaurav Koley
Author-email: gaurav@koley.in
Requires-Python: >=3.11,<4.0
Classifier: Development Status :: 3 - Alpha
Classifier: Intended Audience :: Developers
Classifier: License :: OSI Approved :: MIT License
Classifier: Programming Language :: Python :: 3
Classifier: Programming Language :: Python :: 3.11
Classifier: Programming Language :: Python :: 3.12
Classifier: Topic :: Scientific/Engineering :: Artificial Intelligence
Provides-Extra: all-cpu
Provides-Extra: all-gpu
Provides-Extra: anthropic
Provides-Extra: chroma
Provides-Extra: faiss
Provides-Extra: faiss-gpu
Provides-Extra: huggingface
Provides-Extra: minimal
Provides-Extra: openai
Provides-Extra: vector-stores
Provides-Extra: vector-stores-gpu
Provides-Extra: vertexai
Requires-Dist: aiofiles (==22.1.0)
Requires-Dist: aiohttp (>=3.9.1,<4.0.0)
Requires-Dist: anthropic (>=0.41.0,<1) ; extra == "anthropic" or extra == "all-cpu" or extra == "all-gpu"
Requires-Dist: anyio (>=4.4.0,<5.0.0)
Requires-Dist: asyncio (>=3.4.3,<4.0.0)
Requires-Dist: browser-use (>=0.1.40,<0.2.0)
Requires-Dist: chromadb (>=0.4.0,<0.5.0) ; extra == "chroma" or extra == "vector-stores" or extra == "vector-stores-gpu" or extra == "all-cpu" or extra == "all-gpu"
Requires-Dist: faiss-cpu (>=1.7.0,<2.0.0) ; extra == "faiss" or extra == "vector-stores" or extra == "minimal" or extra == "all-cpu"
Requires-Dist: google-cloud-aiplatform (>=1.25.0,<2.0.0) ; extra == "vertexai" or extra == "all-cpu" or extra == "all-gpu"
Requires-Dist: google-generativeai (>=0.8.4,<0.9.0)
Requires-Dist: langchain-community (>=0.3.18,<0.4.0)
Requires-Dist: networkx (>=3.2.1,<4.0.0)
Requires-Dist: numpy (>=1.24.0,<2.0.0)
Requires-Dist: openai (>=1.0.0,<2.0.0) ; extra == "openai" or extra == "minimal" or extra == "all-cpu" or extra == "all-gpu"
Requires-Dist: pandas (>=2.2.3,<3.0.0)
Requires-Dist: pillow (>=11.1.0,<12.0.0)
Requires-Dist: pinecone (>=6.0.1,<7.0.0)
Requires-Dist: protobuf (>=4.21.6,<5.0)
Requires-Dist: python-dotenv (>=1.0.1,<2.0.0)
Requires-Dist: scipy (>=1.15.2,<2.0.0)
Requires-Dist: tiktoken (>=0.7,<1) ; extra == "openai" or extra == "minimal" or extra == "all-cpu" or extra == "all-gpu"
Requires-Dist: torch (>=2.0.0,<3.0.0) ; extra == "huggingface" or extra == "all-cpu" or extra == "all-gpu"
Requires-Dist: transformers (>=4.30.0,<5.0.0) ; extra == "huggingface" or extra == "all-cpu" or extra == "all-gpu"
Requires-Dist: typing-extensions (>=4.5.0,<5.0.0)
Project-URL: Repository, https://github.com/arkokoley/manas
